srun_swpu_cli/__init__.py
srun_swpu_cli/cli.py
srun_swpu_cli-0.1.1.dist-info/LICENSE
srun_swpu_cli-0.1.1.dist-info/METADATA
srun_swpu_cli-0.1.1.dist-info/WHEEL
srun_swpu_cli-0.1.1.dist-info/entry_points.txt
srun_swpu_cli-0.1.1.dist-info/top_level.txt
srun_swpu_cli-0.1.1.dist-info/RECORD
