Metadata-Version: 2.1
Name: srun-swpu-cli
Version: 0.1.1
Summary: SWPU SRun Network Authentication CLI
Home-page: https://github.com/JustACP/srun-swpu-cli
Author: RE1IFE
Author-email: me@re1ife.top
License: GPL-3.0
Classifier: Programming Language :: Python :: 3
Classifier: Programming Language :: Python :: 3.7
Classifier: Programming Language :: Python :: 3.8
Classifier: Programming Language :: Python :: 3.9
Classifier: License :: OSI Approved :: GNU General Public License v3 (GPLv3)
Classifier: Operating System :: OS Independent
Requires-Python: >=3.7
License-File: LICENSE
Requires-Dist: srun-swpu>=0.1.0
Requires-Dist: rich>=13.0.0
